dirganize/__init__.py
dirganize/cli.py
dirganize/conf.py
dirganize/dirganize.py
dirganize-0.1.0.dist-info/entry_points.txt
dirganize-0.1.0.dist-info/LICENSE
dirganize-0.1.0.dist-info/WHEEL
dirganize-0.1.0.dist-info/METADATA
dirganize-0.1.0.dist-info/RECORD
